LICENSE
MANIFEST.in
README.md
setup.py
perfmon/__init__.py
perfmon/perfmon_int.i
perfmon/perfmon_int.py
perfmon/pmu.py
perfmon/session.py
performance_features/__init__.py
performance_features/compare.py
performance_features/events.py
performance_features/profiler.py
performance_features/workload.cpp
performance_features/workload.h
performance_features/workload.i
performance_features/workload.py
performance_features.egg-info/PKG-INFO
performance_features.egg-info/SOURCES.txt
performance_features.egg-info/dependency_links.txt
performance_features.egg-info/requires.txt
performance_features.egg-info/top_level.txt