Metadata-Version: 2.1
Name: performance-features
Version: 0.2.6
Summary: perf event wrapper for python
Home-page: https://github.com/VitorRamos/performance_features
Author: Vitor Ramos
Author-email: ramos.vitor89@gmail.com
Classifier: Programming Language :: Python :: 3
Classifier: Operating System :: POSIX :: Linux
License-File: LICENSE
